pytest_kwparametrize/__init__.py
pytest_kwparametrize/plugin.py
pytest_kwparametrize/version.py
pytest_kwparametrize-0.0.3.dist-info/LICENSE
pytest_kwparametrize-0.0.3.dist-info/METADATA
pytest_kwparametrize-0.0.3.dist-info/WHEEL
pytest_kwparametrize-0.0.3.dist-info/entry_points.txt
pytest_kwparametrize-0.0.3.dist-info/top_level.txt
pytest_kwparametrize-0.0.3.dist-info/RECORD
