Metadata-Version: 2.1
Name: pytest-kwparametrize
Version: 0.0.3
Summary: Alternate syntax for @pytest.mark.parametrize with test cases as dictionaries and default value fallbacks
Home-page: https://github.com/akaihola/pytest-kwparametrize
Author: Antti Kaihola
Author-email: 13725+akaihola@users.noreply.github.com
License: MIT
Project-URL: Source Code, https://github.com/akaihola/pytest-kwparametrize
Project-URL: Change Log, https://github.com/akaihola/pytest-kwparametrize/blob/master/CHANGES.rst
Platform: UNKNOWN
Classifier: Programming Language :: Python :: 3 :: Only
Classifier: Programming Language :: Python :: 3.6
Classifier: Programming Language :: Python :: 3.7
Classifier: Programming Language :: Python :: 3.8
Classifier: Programming Language :: Python :: 3.9
Requires-Dist: pytest (>=6)
Requires-Dist: typing-extensions ; python_version < "3.8"
Provides-Extra: documentation
Requires-Dist: pallets-sphinx-themes ; extra == 'documentation'
Requires-Dist: pygments-pytest ; extra == 'documentation'
Requires-Dist: sphinx ; extra == 'documentation'
Provides-Extra: testing
Requires-Dist: black ; extra == 'testing'
Requires-Dist: flake8 ; extra == 'testing'
Requires-Dist: isort ; extra == 'testing'
Requires-Dist: pylint ; extra == 'testing'
